<IdIdioma>1</IdIdioma>
<AbreviacaoIdioma>PT-BR<AbreviacaoIdioma/>
<DescricaoIdioma>Português</DescricaoIdioma>
<Situacao>true</Situacao>

<IdIdioma>2</IdIdioma>
<AbreviacaoIdioma>FR</AbreviacaoIdioma>
<DescricaoIdioma>Francês</DescricaoIdioma>
<Situacao>true</Situacao>

<IdIdioma>3</IdIdioma>
<AbreviacaoIdioma>EN-US</AbreviacaoIdioma>
<DescricaoIdioma>Inglês</DescricaoIdioma>
<Situacao>true</Situacao>

<IdIdioma>4</IdIdioma>
<AbreviacaoIdioma>ES</AbreviacaoIdioma>
<DescricaoIdioma>Espanhol</DescricaoIdioma>
<Situacao>true</Situacao>

<IdIdioma>5</IdIdioma>
<AbreviacaoIdioma>DE</AbreviacaoIdioma>
<DescricaoIdioma>Alemão</DescricaoIdioma>
<Situacao>true</Situacao>
